xontrib/history_encrypt/__init__.py
xontrib/history_encrypt/base64.py
xontrib/history_encrypt/fernet.py
xontrib_history_encrypt-0.0.9.dist-info/LICENSE
xontrib_history_encrypt-0.0.9.dist-info/METADATA
xontrib_history_encrypt-0.0.9.dist-info/WHEEL
xontrib_history_encrypt-0.0.9.dist-info/top_level.txt
xontrib_history_encrypt-0.0.9.dist-info/RECORD
