Metadata-Version: 2.1
Name: xontrib-history-encrypt
Version: 0.0.9
Summary: History backend that can encrypt the xonsh shell commands history.
Home-page: https://github.com/anki-code/xontrib-history-encrypt
Author: anki-code
Author-email: no@no.no
License: MIT
Project-URL: Documentation, https://github.com/anki-code/xontrib-history-encrypt/blob/master/README.md
Project-URL: Code, https://github.com/anki-code/xontrib-history-encrypt
Project-URL: Issue tracker, https://github.com/anki-code/xontrib-history-encrypt/issues
Platform: any
Classifier: Programming Language :: Python :: 3
Classifier: Programming Language :: Python :: 3.6
Classifier: Programming Language :: Python :: 3.7
Classifier: Programming Language :: Python :: 3.8
Classifier: Programming Language :: Python :: 3.9
Classifier: License :: OSI Approved :: MIT License
Classifier: Operating System :: OS Independent
Classifier: Topic :: System :: Shells
Classifier: Topic :: System :: System Shells
Classifier: Topic :: Terminals
Requires-Python: >=3.6
Requires-Dist: xonsh
Requires-Dist: cryptography
Requires-Dist: ujson
